{
  "configVersion": 1,
  "timestamp": 1703350735716,
  "index": "https://ngx-canvas.github.io/docs/index.html",
  "assetGroups": [
    {
      "name": "app",
      "installMode": "prefetch",
      "updateMode": "prefetch",
      "cacheQueryOptions": {
        "ignoreVary": true
      },
      "urls": [
        "https://ngx-canvas.github.io/docs/298.f2e89db603d0aa76.js",
        "https://ngx-canvas.github.io/docs/619.2d501a96ae80d83d.js",
        "https://ngx-canvas.github.io/docs/808.7479d683ec7a5bae.js",
        "https://ngx-canvas.github.io/docs/favicon.ico",
        "https://ngx-canvas.github.io/docs/index.html",
        "https://ngx-canvas.github.io/docs/main.6413b12e19a2b753.js",
        "https://ngx-canvas.github.io/docs/manifest.webmanifest",
        "https://ngx-canvas.github.io/docs/polyfills.1180ee621ef3ff08.js",
        "https://ngx-canvas.github.io/docs/runtime.2fe6f2ec6364df99.js",
        "https://ngx-canvas.github.io/docs/styles.cdd9f1216a2d2217.css"
      ],
      "patterns": []
    },
    {
      "name": "assets",
      "installMode": "lazy",
      "updateMode": "prefetch",
      "cacheQueryOptions": {
        "ignoreVary": true
      },
      "urls": [
        "https://ngx-canvas.github.io/docs/Bungee-Regular.6fa9be062cafc884.ttf",
        "https://ngx-canvas.github.io/docs/assets/Bungee/Bungee-Regular.ttf",
        "https://ngx-canvas.github.io/docs/assets/Bungee/OFL.txt",
        "https://ngx-canvas.github.io/docs/assets/data.json",
        "https://ngx-canvas.github.io/docs/assets/donate.png",
        "https://ngx-canvas.github.io/docs/assets/github.png",
        "https://ngx-canvas.github.io/docs/assets/html.minifier.js",
        "https://ngx-canvas.github.io/docs/assets/icons/icon-128x128.png",
        "https://ngx-canvas.github.io/docs/assets/icons/icon-144x144.png",
        "https://ngx-canvas.github.io/docs/assets/icons/icon-152x152.png",
        "https://ngx-canvas.github.io/docs/assets/icons/icon-192x192.png",
        "https://ngx-canvas.github.io/docs/assets/icons/icon-384x384.png",
        "https://ngx-canvas.github.io/docs/assets/icons/icon-512x512.png",
        "https://ngx-canvas.github.io/docs/assets/icons/icon-72x72.png",
        "https://ngx-canvas.github.io/docs/assets/icons/icon-96x96.png",
        "https://ngx-canvas.github.io/docs/assets/prettify.js"
      ],
      "patterns": []
    }
  ],
  "dataGroups": [],
  "hashTable": {
    "https://ngx-canvas.github.io/docs/298.f2e89db603d0aa76.js": "6c017a4ede3c03f78978f966f08ef818d398e3d6",
    "https://ngx-canvas.github.io/docs/619.2d501a96ae80d83d.js": "4c3bb7de2b7d25e16c8c2e0cf4c5a54eaf935fae",
    "https://ngx-canvas.github.io/docs/808.7479d683ec7a5bae.js": "31f13523dcbedbb58c5bfbc3cec5e29e43ac22c9",
    "https://ngx-canvas.github.io/docs/Bungee-Regular.6fa9be062cafc884.ttf": "5229858062d1cc9c3b96abf7a23c4fca2a78efd5",
    "https://ngx-canvas.github.io/docs/assets/Bungee/Bungee-Regular.ttf": "5229858062d1cc9c3b96abf7a23c4fca2a78efd5",
    "https://ngx-canvas.github.io/docs/assets/Bungee/OFL.txt": "016b0312263fdfa61f13d700037415b426ab63af",
    "https://ngx-canvas.github.io/docs/assets/data.json": "e87337eebe114a0c90cf6c444990769e94f2f768",
    "https://ngx-canvas.github.io/docs/assets/donate.png": "882291827755828638da5fd74a2fddbc2a5a1010",
    "https://ngx-canvas.github.io/docs/assets/github.png": "746a80bdc9994e56c90d5dba6a719e3103c46748",
    "https://ngx-canvas.github.io/docs/assets/html.minifier.js": "4d88a26861dc6303eb96f3f6b7dd76d3bb0d3878",
    "https://ngx-canvas.github.io/docs/assets/icons/icon-128x128.png": "1fef6598712cbb65dfd7b5b87e973db6efee6f29",
    "https://ngx-canvas.github.io/docs/assets/icons/icon-144x144.png": "c5678a1c8d58ee123235a0bf64214779fa403012",
    "https://ngx-canvas.github.io/docs/assets/icons/icon-152x152.png": "b808f19b9c361cfa5abd2bd7638d55fbbaeb02a7",
    "https://ngx-canvas.github.io/docs/assets/icons/icon-192x192.png": "463d6db00887bdc0ebbc7d83c4c1db2e03606aef",
    "https://ngx-canvas.github.io/docs/assets/icons/icon-384x384.png": "b494841b56e46583a03354fa439fecadb2966636",
    "https://ngx-canvas.github.io/docs/assets/icons/icon-512x512.png": "aab30a36d757cde9446370db6347affd7a559fc1",
    "https://ngx-canvas.github.io/docs/assets/icons/icon-72x72.png": "d36179f05fea57538d1852c1a8f696b363c31ce7",
    "https://ngx-canvas.github.io/docs/assets/icons/icon-96x96.png": "a924024e4e1237dd5dc221a4d3bd5df4e3eefba0",
    "https://ngx-canvas.github.io/docs/assets/prettify.js": "c8b3889f6a71622539e5bc4db511b934cb62b6e0",
    "https://ngx-canvas.github.io/docs/favicon.ico": "4c50c893762991a06a84b22e5641ed6ee5037734",
    "https://ngx-canvas.github.io/docs/index.html": "91faa26bbb624f662ae1a3fb151f232b7f2c6ef5",
    "https://ngx-canvas.github.io/docs/main.6413b12e19a2b753.js": "4b29f8f76a282f4e257f7f15dc567feb9df92221",
    "https://ngx-canvas.github.io/docs/manifest.webmanifest": "7f62b3f33b271993c036cd8a876fedf216208fe5",
    "https://ngx-canvas.github.io/docs/polyfills.1180ee621ef3ff08.js": "628a7a4cfd11f3b19ec1e7074c7e8a0dfd71d50a",
    "https://ngx-canvas.github.io/docs/runtime.2fe6f2ec6364df99.js": "649d49937da89302ce40fab80882b3018e165089",
    "https://ngx-canvas.github.io/docs/styles.cdd9f1216a2d2217.css": "a1e326dde85fdb337d1f1c815b06c099e4773755"
  },
  "navigationUrls": [
    {
      "positive": true,
      "regex": "^\\/.*$"
    },
    {
      "positive": false,
      "regex": "^\\/(?:.+\\/)?[^/]*\\.[^/]*$"
    },
    {
      "positive": false,
      "regex": "^\\/(?:.+\\/)?[^/]*__[^/]*$"
    },
    {
      "positive": false,
      "regex": "^\\/(?:.+\\/)?[^/]*__[^/]*\\/.*$"
    }
  ],
  "navigationRequestStrategy": "performance"
}